prodmx/__init__.py
prodmx/build.py
prodmx/build_pro_arc.py
prodmx/build_pro_dom.py
prodmx/config.ini
prodmx/matrix.py
prodmx/pfam_filter.py
prodmx/util.py
prodmx-0.1.0.dist-info/LICENSE
prodmx-0.1.0.dist-info/METADATA
prodmx-0.1.0.dist-info/WHEEL
prodmx-0.1.0.dist-info/entry_points.txt
prodmx-0.1.0.dist-info/top_level.txt
prodmx-0.1.0.dist-info/RECORD
