Metadata-Version: 2.1
Name: prodmx
Version: 0.1.0
Summary: Protein Functional Domain Analysis based on Compressed Sparse Matrix
Home-page: https://github.com/visanuwan/prodmx
Author: Visanu Wanchai
Author-email: visanuw86@gmail.com
License: MIT
Platform: UNKNOWN
Classifier: Development Status :: 4 - Beta
Classifier: Intended Audience :: Science/Research
Classifier: License :: OSI Approved :: MIT License
Classifier: Topic :: Scientific/Engineering :: Bio-Informatics
Requires-Dist: pandas (>=0.25.1)
Requires-Dist: h5py (>=2.9.0)
Requires-Dist: numpy (>=1.17.2)
Requires-Dist: tqdm (>=4.36.1)
Requires-Dist: scipy (>=1.3.1)
